fraplustree
