Metadata-Version: 2.1
Name: fraplustree
Version: 1.1.1
Summary: A package draws tree and fractals
Author: Guido Xhindoli
Author-email: <mail@gmail.com>
Keywords: fraplustree,SDA,fra,tree
Classifier: Development Status :: 1 - Planning
Classifier: Intended Audience :: Developers
Classifier: Programming Language :: Python :: 3
Classifier: Operating System :: Unix
Classifier: Operating System :: MacOS :: MacOS X
Classifier: Operating System :: Microsoft :: Windows
Requires-Dist: PythonTurtle==0.3.2
